odoo8_addon_stock_picking_manual_procurement_group-8.0.1.0.0-py2.7-nspkg.pth
odoo_addons/stock_picking_manual_procurement_group/__openerp__.py
odoo_addons/stock_picking_manual_procurement_group/__init__.py
odoo_addons/stock_picking_manual_procurement_group/README.rst
odoo_addons/stock_picking_manual_procurement_group/models/stock_move.py
odoo_addons/stock_picking_manual_procurement_group/models/__init__.py
odoo_addons/stock_picking_manual_procurement_group/models/stock_picking.py
odoo_addons/stock_picking_manual_procurement_group/views/stock_picking_views.xml
odoo_addons/stock_picking_manual_procurement_group/tests/__init__.py
odoo_addons/stock_picking_manual_procurement_group/tests/test_stock_picking.py
odoo_addons/stock_picking_manual_procurement_group/static/description/icon.png
odoo8_addon_stock_picking_manual_procurement_group-8.0.1.0.0.dist-info/top_level.txt
odoo8_addon_stock_picking_manual_procurement_group-8.0.1.0.0.dist-info/WHEEL
odoo8_addon_stock_picking_manual_procurement_group-8.0.1.0.0.dist-info/RECORD
odoo8_addon_stock_picking_manual_procurement_group-8.0.1.0.0.dist-info/metadata.json
odoo8_addon_stock_picking_manual_procurement_group-8.0.1.0.0.dist-info/DESCRIPTION.rst
odoo8_addon_stock_picking_manual_procurement_group-8.0.1.0.0.dist-info/METADATA
odoo8_addon_stock_picking_manual_procurement_group-8.0.1.0.0.dist-info/namespace_packages.txt
